torchnorms/__init__.py
torchnorms/negations/__init__.py
torchnorms/negations/base.py
torchnorms/negations/classic.py
torchnorms/negations/weber.py
torchnorms/negations/yager.py
torchnorms/tconorms/__init__.py
torchnorms/tconorms/base.py
torchnorms/tconorms/classic.py
torchnorms/tconorms/dombi.py
torchnorms/tconorms/dubois.py
torchnorms/tconorms/hamacher.py
torchnorms/tconorms/ss.py
torchnorms/tconorms/weber.py
torchnorms/tconorms/yager.py
torchnorms/tnorms/__init__.py
torchnorms/tnorms/aa.py
torchnorms/tnorms/additive_generator.py
torchnorms/tnorms/base.py
torchnorms/tnorms/classic.py
torchnorms/tnorms/dombi.py
torchnorms/tnorms/dubois.py
torchnorms/tnorms/frank.py
torchnorms/tnorms/hamacher.py
torchnorms/tnorms/laf.py
torchnorms/tnorms/neural.py
torchnorms/tnorms/siamese_laf.py
torchnorms/tnorms/ss.py
torchnorms/tnorms/weber.py
torchnorms/tnorms/yager.py
torchnorms-1.5.8.dist-info/LICENSE
torchnorms-1.5.8.dist-info/METADATA
torchnorms-1.5.8.dist-info/WHEEL
torchnorms-1.5.8.dist-info/top_level.txt
torchnorms-1.5.8.dist-info/RECORD
